mahdi/__init__.py
MAHDI_Fire-5.6.dist-info/LICENSE
MAHDI_Fire-5.6.dist-info/METADATA
MAHDI_Fire-5.6.dist-info/WHEEL
MAHDI_Fire-5.6.dist-info/top_level.txt
MAHDI_Fire-5.6.dist-info/RECORD
