Metadata-Version: 2.1
Name: MAHDI_Fire
Version: 5.6
Summary: this is a simple pip modul and test
License-File: LICENSE
